<?xml version="1.0" encoding="utf-8" ?>
<Locale>
	<Name>Deutsch (de-DE)</Name>
	<Buttons>
		<AddNewAccount>Konto hinzufügen</AddNewAccount>
		<Browse>Durchsuchen...</Browse>
		<Cancel>Abbrechen</Cancel>
		<Default>Standard</Default>
		<Edit>Bearbeiten</Edit>
		<Next>Weiter</Next>
		<OK>OK</OK>
		<Save>Speichern</Save>
		<LetsGo>Los geht's!</LetsGo>
		<Sweet>Cool, danke</Sweet>
		<Remove>Gewähltes Konto löschen</Remove>
	</Buttons>
	<Labels>
		<About>Über Gmail Notifier Plus</About>
		<Additional>Zusätzliche Einstellungen</Additional>
		<BrowseDialog>Nach neuem Benachrichtigungston suchen.</BrowseDialog>
		<CheckLogin>Bitte Kontoeinstellungen prüfen.</CheckLogin>
		<CheckMail>Auf neue Mail prüfen</CheckMail>
		<Compose>Mail verfassen</Compose>
		<Configuration>Konten verwalten</Configuration>
		<ConfigurationShort>Einstellungen ändern</ConfigurationShort>
		<Connecting>Prüfung auf neue Mails läuft...</Connecting>
		<ConnectionUnavailable>Bitte Netzwerkverbindung überprüfen</ConnectionUnavailable>
		<CustomSound>Angepasst...</CustomSound>
		<DefaultSound>Standard</DefaultSound>
		<Edit>Kontoinformation bearbeiten</Edit>
		<Error>Ein Konto mit diesem Benutzernamen existiert bereits. Bitte geben Sie einen anderen Benutzernamen an.</Error>
		<Inbox>Posteingang aufrufen</Inbox>
		<Interval>Prüfintervall:</Interval>
		<Language>Anzeigesprache:</Language>
		<Login>Benutzername:</Login>
		<Minutes>Minute(n)</Minutes>
		<No>Nein</No>
		<NoAccount>Bitte ein Konto erstellen.</NoAccount>
		<NoMail>Keine neuen Mails</NoMail>
		<NoSound>Kein</NoSound>
		<NoSubject>(kein Betreff)</NoSubject>
		<OSErrorContent>Diese Software wurde ausschließlich für Windows 7 entwickelt.</OSErrorContent>
		<OSErrorTitle>Fehler mit Betriebssystemkompatibilität</OSErrorTitle>
		<Password>Kennwort:</Password>
		<RemoveConfirmation>Möchten Sie dieses Konto wirklich löschen?</RemoveConfirmation>
		<RemoveConfirmationTitle>Konto löschen</RemoveConfirmationTitle>
		<Sound>Soundbenachrichtigung</Sound>
		<Unread>Ungelesen</Unread>
		<WaveFiles>Wave-Datei</WaveFiles>
		<Yes>Ja</Yes>
		<AccountsIntro>Klicken Sie auf ein Konto auf der linken Seite auf Ihre individuellen Konten verwalten. Klicken Sie auf die Schaltfläche unten, um ein neues Konto hinzuzufügen.</AccountsIntro>
		<AccountsIntroNone>Willkommen bei Gmail Notifier Plus.\n\nWenn loszulegen, klicken Sie bitte auf die Schaltfläche unten, um ein neues Konto hinzuzufügen.</AccountsIntroNone>
	</Labels>
	<Tooltips>
		<About>Über Gmail Notifier Plus</About>
		<Add>Konto hinzufügen</Add>
		<Inbox>Posteingang</Inbox>
		<Next>Weiter</Next>
		<OpenMail>Posteingang öffnen</OpenMail>
		<Previous>Zurück</Previous>
		<Settings>Einstellungen</Settings>
	</Tooltips>
	<Config>
		<Accounts>Konten</Accounts>
		<Appearance>Aussehen</Appearance>
		<General>Allgemeine</General>
		<Panels>
			<Accounts>Verwalten Sie Ihre Konten</Accounts>
			<AccountWarn>Klick retten wird sofort sparen alle Änderungen an diesem Konto.</AccountWarn>
			<Appearance>Erzähl Gmail Notifier Plus, wie zu handeln und suchen</Appearance>
			<General>Bread n 'Butter-Einstellungen für Google Mail Notifier Plus</General>
			<NewAccount>Neues Konto hinzufügen</NewAccount>
		</Panels>
	</Config>
	<Checkboxes>
		<FlashTaskbar>Flash-Taskleiste für neue E-Mail</FlashTaskbar>
		<ShowTray>Zeige E-Mail zählen in der Taskleiste</ShowTray>
		<ShowToast>Zeige Toast Benachrichtigungen über neue E-Mail</ShowToast>
		<CheckUpdates>Überprüfung auf neue Versionen</CheckUpdates>
	</Checkboxes>
</Locale>