<?xml version="1.0" encoding="windows-1251" ?>
<Locale>
	<Name>Русский (ru-RU)</Name>
	<Buttons>
		<AddNewAccount>Добавить учетную запись</AddNewAccount>
		<Browse>Обзор...</Browse>
		<Cancel>Отмена</Cancel>
		<Default>По умолчанию</Default>
		<Edit>Изменить</Edit>
		<Next>Далее</Next>
		<OK>OK</OK>
		<Save>Сохранить</Save>
		<LetsGo>Поехали!</LetsGo>
		<Sweet>Чудно, Спасибо</Sweet>
		<Remove>Удалить аккаунт</Remove>
	</Buttons>
	<Labels>
		<About>О программе Gmail Notifier Plus</About>
		<Additional>Дополнительно</Additional>
		<BrowseDialog>Выбрать звук уведомления.</BrowseDialog>
		<CheckLogin>Пожалуйста, проверьте свое сетевое подключение.</CheckLogin>
		<CheckMail>Проверить почту</CheckMail>
		<Compose>Написать письмо</Compose>
		<Configuration>Управление учетными записями</Configuration>
		<ConfigurationShort>Настройки</ConfigurationShort>
		<Connecting>Идет проверка почта...</Connecting>
		<ConnectionUnavailable>Пожалуйста, проверьте свое сетевое подключение</ConnectionUnavailable>
		<CustomSound>Выбрать...</CustomSound>
		<DefaultSound>По умолчанию</DefaultSound>
		<Edit>Изменить учетную запись</Edit>
		<Error>Учетная запись с таким именем уже существует. Пожалуйста, введите другое имя учетной записи.</Error>
		<Help>Help Wiki</Help>
		<Inbox>Входящие</Inbox>
		<Interval>Проверять каждые:</Interval>
		<Language>Выбрать язык:</Language>
		<Login>Имя учетной записи:</Login>
		<Minutes>минут(ы)</Minutes>
		<No>Нет</No>
		<NoAccount>Пожалуйста, настройте учетную запись.</NoAccount>
		<NoMail>Новых писем нет</NoMail>
		<NoSound>Без звука</NoSound>
		<NoSubject>(без темы)</NoSubject>
		<OSErrorContent>Данная программа работает только на Windows 7.</OSErrorContent>
		<OSErrorTitle>Ошибка совместимости операционной системы</OSErrorTitle>
		<Password>Пароль:</Password>
		<RemoveConfirmation>Вы действительно хотите удалить эту учетную запись?</RemoveConfirmation>
		<RemoveConfirmationTitle>Удалить учетную запись</RemoveConfirmationTitle>
		<Sound>Звук уведомления</Sound>
		<Unread>Непрочтенные</Unread>
		<WaveFiles>.WAV файлов</WaveFiles>
		<Yes>Да</Yes>
		<AccountsIntro>Нажмите счета на левой управлять своими лицевыми счетами. Нажмите на кнопку ниже, чтобы добавить новую учетную запись.</AccountsIntro>
		<AccountsIntroNone>Добро пожаловать в Gmail Notifier Plus. Для начала, пожалуйста, нажмите на кнопку ниже, чтобы добавить новую учетную запись.</AccountsIntroNone>
	</Labels>
	<Tooltips>
		<About>О Gmail Notifier Plus</About>
		<Add>Добавить новую учетную запись</Add>
		<Inbox>Входящие</Inbox>
		<Next>Следующая</Next>
		<OpenMail>Откройте папку "Входящие</OpenMail>
		<Previous>Предыдущая</Previous>
		<Settings>Настройки</Settings>
	</Tooltips>
	<Config>
		<Accounts>Счетов</Accounts>
		<Appearance>Внешний вид</Appearance>
		<General>Генеральная</General>
		<Panels>
			<Accounts>Управлять своими счетами</Accounts>
			<Appearance>Скажите Gmail Notifier Plus, как действовать и Смотри</Appearance>
			<General>Масло Хлеб п настройки для Gmail Notifier Plus</General>
			<NewAccount>Добавить новую учетную запись</NewAccount>
		</Panels>
	</Config>
	<Checkboxes>
		<FlashTaskbar>Flash задач наличие новых писем</FlashTaskbar>
		<ShowTray>Показать Email кол в системном трее</ShowTray>
		<ShowToast>Показать Тост уведомления о Email Новые</ShowToast>
		<CheckUpdates>Проверить наличие обновлений</CheckUpdates>
	</Checkboxes>
</Locale>